Metadata-Version: 2.1
Name: cbrrr
Version: 1.0.1
Summary: A reasonably fast DAG-CBOR encoder/decoder for Python
Author-email: David Buchanan <d@vidbuchanan.co.uk>
Project-URL: Homepage, https://github.com/DavidBuchanan314/dag-cbrrr
Project-URL: Issues, https://github.com/DavidBuchanan314/dag-cbrrr/issues
Classifier: Programming Language :: Python :: 3
Classifier: Programming Language :: Python :: 3.7
Classifier: Programming Language :: Python :: 3.8
Classifier: Programming Language :: Python :: 3.9
Classifier: Programming Language :: Python :: 3.10
Classifier: Programming Language :: Python :: 3.11
Classifier: Programming Language :: Python :: 3.12
Classifier: License :: OSI Approved :: MIT License
Classifier: Operating System :: OS Independent
Requires-Python: >=3.7
License-File: LICENSE
Provides-Extra: fixtures
Requires-Dist: base58; extra == "fixtures"
Provides-Extra: fuzz
Requires-Dist: atheris; extra == "fuzz"
